lulu/__init__.py
lapizlazuli-0.0.1.dist-info/METADATA
lapizlazuli-0.0.1.dist-info/WHEEL
lapizlazuli-0.0.1.dist-info/top_level.txt
lapizlazuli-0.0.1.dist-info/RECORD
